ckanext_keycloak-0.0.1-py2.7-nspkg.pth
ckanext/keycloak/__init__.py
ckanext/keycloak/helper.py
ckanext/keycloak/plugin.py
ckanext_keycloak-0.0.1.dist-info/LICENSE
ckanext_keycloak-0.0.1.dist-info/METADATA
ckanext_keycloak-0.0.1.dist-info/WHEEL
ckanext_keycloak-0.0.1.dist-info/entry_points.txt
ckanext_keycloak-0.0.1.dist-info/namespace_packages.txt
ckanext_keycloak-0.0.1.dist-info/top_level.txt
ckanext_keycloak-0.0.1.dist-info/RECORD
